r0c/__init__.py
r0c/__main__.py
r0c/__version__.py
r0c/chat.py
r0c/diag.py
r0c/inetcat.py
r0c/irc.py
r0c/itelnet.py
r0c/ivt100.py
r0c/user.py
r0c/util.py
r0c/world.py
r0c-1.6.1.data/data/share/doc/r0c/LICENSE
r0c-1.6.1.data/data/share/doc/r0c/README.md
r0c-1.6.1.data/data/share/doc/r0c/clients/bash.sh
r0c-1.6.1.data/data/share/doc/r0c/clients/powershell.ps1
r0c-1.6.1.data/data/share/doc/r0c/help/help-about.md
r0c-1.6.1.data/data/share/doc/r0c/help/help-commands.md
r0c-1.6.1.data/data/share/doc/r0c/help/help-hotkeys.md
r0c-1.6.1.data/data/share/doc/r0c/help/help-topics.md
r0c-1.6.1.data/data/share/doc/r0c/help/help-ui.md
r0c-1.6.1.data/data/share/doc/r0c/help/todo.md
r0c-1.6.1.dist-info/LICENSE
r0c-1.6.1.dist-info/METADATA
r0c-1.6.1.dist-info/WHEEL
r0c-1.6.1.dist-info/entry_points.txt
r0c-1.6.1.dist-info/top_level.txt
r0c-1.6.1.dist-info/RECORD
